kitchenai_sdk/__init__.py
kitchenai_sdk/kitchenai.py
kitchenai_sdk-0.1.4.dist-info/METADATA
kitchenai_sdk-0.1.4.dist-info/WHEEL
kitchenai_sdk-0.1.4.dist-info/RECORD
